astra/__init__.py
astra/activation.py
astra/feed_forward.py
astra/gpt_model.py
astra/layer_norm.py
astra/model.py
astra/multi_head_attention.py
astra/tokenizer.py
astra/transformer_block.py
astra_llm-0.1.21.dist-info/LICENSE
astra_llm-0.1.21.dist-info/METADATA
astra_llm-0.1.21.dist-info/WHEEL
astra_llm-0.1.21.dist-info/top_level.txt
astra_llm-0.1.21.dist-info/RECORD
